<?xml version="1.0" encoding="utf-8"?>
<!-- Copyright 2017 Stein & Gabelgaard ApS
     License AGPL-3.0 or later (http://www.gnu.org/licenses/agpl). -->

<openerp>
<data>

    <record model="ir.ui.view" id="campos_activity_pitag_form_view">
        <field name="name">campos.activity.pitag.form (in campos_activity)</field>
        <field name="model">campos.activity.pitag</field>
        <field name="arch" type="xml">
            <form>
                <header>
                    <!-- TODO -->
                </header>
                <sheet>
                    <!-- TODO -->
                    <group>
                        <field name="name"/>
                    </group>
                </sheet>
                <div class="oe_chatter"></div>
            </form>
        </field>
    </record>

    <record model="ir.ui.view" id="campos_activity_pitag_search_view">
        <field name="name">campos.activity.pitag.search (in campos_activity)</field>
        <field name="model">campos.activity.pitag</field>
        <field name="arch" type="xml">
            <search>
                <!-- TODO -->
            </search>
        </field>
    </record>

    <record model="ir.ui.view" id="campos_activity_pitag_tree_view">
        <field name="name">campos.activity.pitag.tree (in campos_activity)</field>
        <field name="model">campos.activity.pitag</field>
        <field name="arch" type="xml">
            <tree>
                <!-- TODO -->
                <field name="name"/>
            </tree>
        </field>
    </record>

    <record model="ir.actions.act_window" id="campos_activity_pitag_act_window">
        <field name="name">Campos Activity Pitag</field> <!-- TODO -->
        <field name="res_model">campos.activity.pitag</field>
        <field name="view_mode">tree,form</field>
        <field name="domain">[]</field>
        <field name="context">{}</field>
    </record>

    <record model="ir.ui.menu" id="campos_activity_pitag_menu">
        <field name="name">Campos Activity Pitag</field>
        <field name="parent_id" ref="xmlid of parent menu"/> <!-- TODO -->
        <field name="action" ref="campos_activity_pitag_act_window"/>
        <field name="sequence" eval="16"/> <!-- TODO -->
    </record>

</data>
</openerp>
